LICENSE.txt
README.md
setup.py
CheckKoreanHoliday/CheckKoreanHoliday.py
CheckKoreanHoliday/__init__.py
CheckKoreanHoliday.egg-info/PKG-INFO
CheckKoreanHoliday.egg-info/SOURCES.txt
CheckKoreanHoliday.egg-info/dependency_links.txt
CheckKoreanHoliday.egg-info/top_level.txt